astinxml/Documenter.py
astinxml/Visitor.py
astinxml/__init__.py
astinxml/__main__.py
astinxml-0.3.dist-info/DESCRIPTION.rst
astinxml-0.3.dist-info/METADATA
astinxml-0.3.dist-info/RECORD
astinxml-0.3.dist-info/WHEEL
astinxml-0.3.dist-info/metadata.json
astinxml-0.3.dist-info/top_level.txt
